README.md
setup.cfg
setup.py
xt/__init__.py
xt.egg-info/PKG-INFO
xt.egg-info/SOURCES.txt
xt.egg-info/dependency_links.txt
xt.egg-info/entry_points.txt
xt.egg-info/not-zip-safe
xt.egg-info/requires.txt
xt.egg-info/top_level.txt
xt/scripts/__init__.py
xt/scripts/cli.py