Metadata-Version: 2.1
Name: xt
Version: 0.1.1
Summary: xForm Tile Coordinates
Home-page: https://github.com/mapbox/xt
Author: Damon Burgett
Author-email: damon@mapbox.com
License: MIT
Platform: UNKNOWN
Provides-Extra: test
